cpwxtract/__about__.py
cpwxtract/__init__.py
cpwxtract/constants.py
cpwxtract/cpw.py
cpwxtract/extract.py
cpwxtract/helpers.py
cpwxtract/io.py
cpwxtract-0.0.2.dist-info/LICENSE.txt
cpwxtract-0.0.2.dist-info/METADATA
cpwxtract-0.0.2.dist-info/WHEEL
cpwxtract-0.0.2.dist-info/top_level.txt
cpwxtract-0.0.2.dist-info/RECORD
