Metadata-Version: 2.1
Name: cpwxtract
Version: 0.0.2
Summary: Permittivity extraction from open-ended coaxial probe measurements
Home-page: https://gitlab.com/benvial/cpwxtract
Author: Benjamin Vial
License: GPL-3.0-or-later
Project-URL: Code, https://gitlab.com/benvial/cpwxtract
Project-URL: Documentation, https://gitlab.com/benvial/cpwxtract
Project-URL: Issues, https://gitlab.com/benvial/cpwxtract/issues
Keywords: electromagnetism,permittivity measurements,coplanar waveguides
Platform: UNKNOWN
Classifier: Development Status :: 4 - Beta
Classifier: Intended Audience :: Science/Research
Classifier: License :: OSI Approved :: GNU General Public License v3 or later (GPLv3+)
Classifier: Operating System :: OS Independent
Classifier: Programming Language :: Python
Classifier: Programming Language :: Python :: 3
Classifier: Programming Language :: Python :: 3.6
Classifier: Programming Language :: Python :: 3.7
Classifier: Programming Language :: Python :: 3.8
Classifier: Programming Language :: Python :: 3.9
Classifier: Topic :: Scientific/Engineering
Classifier: Topic :: Scientific/Engineering :: Mathematics
Classifier: Topic :: Utilities
Requires-Python: >=3.6
License-File: LICENSE.txt
Requires-Dist: numpy (>=1.9)
Requires-Dist: scipy (>=1.0)
Requires-Dist: jax
Requires-Dist: jaxlib
Requires-Dist: nlopt
Requires-Dist: importlib-metadata ; python_version < "3.8"
